autowired/__init__.py
autowired/_component_scan.py
autowired/_container.py
autowired/_context.py
autowired/_exceptions.py
autowired/_logging.py
autowired/_thread_local_cached_property.py
autowired/_typing_utils.py
tests/__init__.py
tests/test_autowired.py
tests/test_component_scan.py
tests/test_thread_local_cached_property.py
tests/test_typing_utils.py
tests/component_scan_test_module/__init__.py
tests/component_scan_test_module/controller.py
tests/component_scan_test_module/file_module.py
tests/component_scan_test_module/test_package/__init__.py
tests/component_scan_test_module/test_package/file_module.py
autowired-0.2.13.dist-info/LICENSE
autowired-0.2.13.dist-info/METADATA
autowired-0.2.13.dist-info/WHEEL
autowired-0.2.13.dist-info/top_level.txt
autowired-0.2.13.dist-info/RECORD
