Metadata-Version: 2.1
Name: autowired
Version: 0.2.13
Summary: A minimalistic dependency injection library for Python
Home-page: https://github.com/npgrosser/autowired
Author: Nicolai Großer
Author-email: nicolai.grosser@googlemail.com
License: MIT
Classifier: Development Status :: 4 - Beta
Classifier: Intended Audience :: Developers
Classifier: Topic :: Software Development :: Libraries
Classifier: License :: OSI Approved :: MIT License
Classifier: Programming Language :: Python :: 3.8
Classifier: Programming Language :: Python :: 3.9
Classifier: Programming Language :: Python :: 3.10
Classifier: Programming Language :: Python :: 3.11
Classifier: Programming Language :: Python :: 3.12
Requires-Python: >=3.8
License-File: LICENSE
